<?xml version="1.0" encoding="UTF-8"?>

<!DOCTYPE configuration
  PUBLIC "-//mybatis.org//DTD Config 3.0//EN"
  "http://mybatis.org/dtd/mybatis-3-config.dtd">
  
<configuration>
	<settings>
        <setting name="jdbcTypeForNull" value="NULL" />
	</settings>
	
	<!-- 매퍼에서 쿼리할대 파라메터로 사용하기 위해서 등록함. -->
	<typeAliases>
		<typeAlias type="kr.co.jhta.dto.ArticleDTO" alias="adto" />
		<typeAlias type="kr.co.jhta.dto.UserDTO" alias="udto" />
		<typeAlias type="kr.co.jhta.dto.GeneralBookDTO" alias="gbdto" />				
		<typeAlias type="kr.co.jhta.dto.RequestWishBookDTO" alias="rwbdto"/>
		<typeAlias type="kr.co.jhta.dto.FavoriteBookDTO" alias="fbdto"/>
		<typeAlias type="kr.co.jhta.dto.BorrowBookDTO" alias="bbdto"/>
		<typeAlias type="kr.co.jhta.dto.LibraryBookDTO" alias="lbdto"/>
		<typeAlias type="kr.co.jhta.dto.PageStartEnd" alias="se"/>
		<typeAlias type="kr.co.jhta.dto.GeneralBookDTO" alias="gbdto"/>
		<!--2020-03-31준영  -->
		<typeAlias type="kr.co.jhta.dto.ReadingRoomDTO" alias="rdto"/>
		<!--2020-04-23준영  -->
		<typeAlias type="kr.co.jhta.dto.RentPlaceIdDTO" alias="rpidto"/>
		
	</typeAliases>

	<!-- <mappers> 어떻게 해도 web-inf 경로가 안먹네... 이쪽에서는 접근 불가능인가봄-->
<!-- 		<mapper resource="/mybatis/mappers/member.xml"/> -->
		<!-- <mapper resource="/WEB-INF/mybatis/mappers/member.xml"/>
 		<mapper resource="/WEB-INF/mybatis/mappers/schedule.xml"/> -->
		<!-- <mapper resource="classpath*:/mapper/*.xml"/> -->
	<!-- </mappers> -->
</configuration>